rpa_sdk/__init__.py
rpa_sdk/py.typed
rpa_sdk/rpa_client.py
rpa_sdk/data/TArchive.py
rpa_sdk/data/TPhysical.py
rpa_sdk/data/TVisit.py
rpa_sdk/data/__init__.py
rpa_sdk/element/__init__.py
rpa_sdk/element/operations_bjyd.py
rpa_sdk/element/operations_gzby.py
rpa_sdk/element/operations_gzhz.py
rpa_sdk/element/operations_gzzc.py
rpa_sdk/kit/ComKit.py
rpa_sdk/kit/DialogKit.py
rpa_sdk/kit/FileKit.py
rpa_sdk/kit/IdCardKit.py
rpa_sdk/kit/MySql.py
rpa_sdk/kit/StrKit.py
rpa_sdk/kit/SysKit.py
rpa_sdk/kit/Utils.py
rpa_sdk/kit/__init__.py
rpa_sdk/kit/enums.py
rpa_sdk/manager/__init__.py
rpa_sdk/manager/base_browser_manager.py
rpa_sdk/manager/base_handler.py
rpa_sdk/manager/browser_factory.py
rpa_sdk/manager/database_manager.py
rpa_sdk/manager/element_operations_factory.py
rpa_sdk/manager/element_operations_interface.py
rpa_sdk/manager/playwright_browser_manager.py
rpa_sdk/manager/selenium_browser_manager.py
rpa_sdk/manager/websocket_manager.py
rpa_sdk-1.1.3.dist-info/METADATA
rpa_sdk-1.1.3.dist-info/WHEEL
rpa_sdk-1.1.3.dist-info/top_level.txt
rpa_sdk-1.1.3.dist-info/RECORD
