Metadata-Version: 2.4
Name: rpa-sdk
Version: 1.1.3
Summary: RPA SDK - 机器人流程自动化软件开发工具包
Author-email: AITMC <support@aitmc.com>
Project-URL: Homepage, https://gitee.com/aitmc/rpa-sdk
Project-URL: Bug Reports, https://gitee.com/aitmc/rpa-sdk/issues
Project-URL: Source, https://gitee.com/aitmc/rpa-sdk
Project-URL: Documentation, https://gitee.com/aitmc/rpa-sdk/wikis
Keywords: rpa,automation,browser,websocket,database
Classifier: Development Status :: 4 - Beta
Classifier: Intended Audience :: Developers
Classifier: Topic :: Software Development :: Libraries :: Python Modules
Classifier: Topic :: Office/Business :: Office Suites
Classifier: License :: OSI Approved :: MIT License
Classifier: Programming Language :: Python :: 3
Classifier: Programming Language :: Python :: 3.8
Classifier: Programming Language :: Python :: 3.9
Classifier: Programming Language :: Python :: 3.10
Classifier: Programming Language :: Python :: 3.11
Classifier: Programming Language :: Python :: 3.12
Classifier: Operating System :: OS Independent
Requires-Python: >=3.8
Requires-Dist: playwright>=1.40.0
Requires-Dist: selenium>=3.150.1
Requires-Dist: websocket-client>=1.6.0
Requires-Dist: PyMySQL>=1.1.0
Requires-Dist: requests>=2.31.0
Requires-Dist: typing-extensions>=4.8.0
Provides-Extra: dev
Requires-Dist: pytest>=7.0.0; extra == "dev"
Requires-Dist: pytest-cov>=4.0.0; extra == "dev"
Requires-Dist: black>=23.0.0; extra == "dev"
Requires-Dist: flake8>=6.0.0; extra == "dev"
Requires-Dist: mypy>=1.0.0; extra == "dev"
Provides-Extra: selenium
Requires-Dist: selenium>=4.15.0; extra == "selenium"
Provides-Extra: parsing
Requires-Dist: beautifulsoup4>=4.12.0; extra == "parsing"
Requires-Dist: lxml>=4.9.0; extra == "parsing"
